{"BTCUSD-2024-12-28": "simple", "ETHUSD-2024-12-28": "simple", "UNIUSD-2024-12-28": "simple", "NVDA-2024-12-28": "simple", "BTCUSD-2024-12-29": "simple", "ETHUSD-2024-12-29": "simple", "UNIUSD-2024-12-29": "simple", "BTCUSD-2024-12-30": "simple", "ETHUSD-2024-12-30": "simple", "UNIUSD-2024-12-30": "simple", "COUR-2024-12-31": "all_signals", "GOOG-2024-12-31": "simple", "TSLA-2024-12-31": "all_signals", "NVDA-2024-12-31": "all_signals", "AAPL-2024-12-31": "simple", "U-2024-12-31": "all_signals", "ADSK-2024-12-31": "simple", "CRWD-2024-12-31": "simple", "ADBE-2024-12-31": "all_signals", "NET-2024-12-31": "simple", "COIN-2024-12-31": "simple", "MSFT-2024-12-31": "all_signals", "META-2024-12-31": "all_signals", "AMZN-2024-12-31": "all_signals", "AMD-2024-12-31": "simple", "INTC-2024-12-31": "all_signals", "LCID-2024-12-31": "all_signals", "QUBT-2024-12-31": "all_signals", "BTCUSD-2024-12-31": "simple", "ETHUSD-2024-12-31": "simple", "UNIUSD-2024-12-31": "simple", "COUR-2025-01-01": "all_signals", "GOOG-2025-01-01": "simple", "TSLA-2025-01-01": "all_signals", "NVDA-2025-01-01": "all_signals", "AAPL-2025-01-01": "all_signals", "U-2025-01-01": "all_signals", "ADSK-2025-01-01": "simple", "CRWD-2025-01-01": "simple", "ADBE-2025-01-01": "all_signals", "NET-2025-01-01": "simple", "COIN-2025-01-01": "simple", "MSFT-2025-01-01": "all_signals", "META-2025-01-01": "all_signals", "AMZN-2025-01-01": "all_signals", "AMD-2025-01-01": "simple", "INTC-2025-01-01": "all_signals", "LCID-2025-01-01": "all_signals", "QUBT-2025-01-01": "all_signals", "BTCUSD-2025-01-01": "simple", "ETHUSD-2025-01-01": "simple", "UNIUSD-2025-01-01": "highlow", "BTCUSD-2025-01-02": "simple", "ETHUSD-2025-01-02": "simple", "UNIUSD-2025-01-02": "simple", "COUR-2025-01-03": "all_signals", "GOOG-2025-01-03": "simple", "TSLA-2025-01-03": "all_signals", "NVDA-2025-01-03": "all_signals", "AAPL-2025-01-03": "all_signals", "U-2025-01-03": "all_signals", "ADSK-2025-01-03": "simple", "CRWD-2025-01-03": "simple", "ADBE-2025-01-03": "all_signals", "NET-2025-01-03": "simple", "COIN-2025-01-03": "simple", "MSFT-2025-01-03": "all_signals", "META-2025-01-03": "all_signals", "AMZN-2025-01-03": "all_signals", "AMD-2025-01-03": "simple", "INTC-2025-01-03": "all_signals", "LCID-2025-01-03": "all_signals", "QUBT-2025-01-03": "all_signals", "BTCUSD-2025-01-03": "simple", "ETHUSD-2025-01-03": "simple", "UNIUSD-2025-01-03": "highlow", "COUR-2025-01-04": "all_signals", "GOOG-2025-01-04": "simple", "TSLA-2025-01-04": "all_signals", "NVDA-2025-01-04": "simple", "AAPL-2025-01-04": "all_signals", "U-2025-01-04": "all_signals", "ADSK-2025-01-04": "simple", "CRWD-2025-01-04": "simple", "ADBE-2025-01-04": "all_signals", "NET-2025-01-04": "simple", "COIN-2025-01-04": "simple", "MSFT-2025-01-04": "all_signals", "META-2025-01-04": "all_signals", "AMZN-2025-01-04": "all_signals", "AMD-2025-01-04": "all_signals", "INTC-2025-01-04": "all_signals", "LCID-2025-01-04": "all_signals", "QUBT-2025-01-04": "all_signals", "BTCUSD-2025-01-04": "simple", "ETHUSD-2025-01-04": "simple", "UNIUSD-2025-01-04": "highlow", "BTCUSD-2025-01-05": "simple", "ETHUSD-2025-01-05": "all_signals", "UNIUSD-2025-01-05": "highlow", "BTCUSD-2025-01-06": "simple", "ETHUSD-2025-01-06": "all_signals", "UNIUSD-2025-01-06": "highlow", "COUR-2025-01-07": "all_signals", "GOOG-2025-01-07": "simple", "TSLA-2025-01-07": "all_signals", "NVDA-2025-01-07": "all_signals", "AAPL-2025-01-07": "all_signals", "U-2025-01-07": "all_signals", "ADSK-2025-01-07": "simple", "CRWD-2025-01-07": "simple", "ADBE-2025-01-07": "all_signals", "NET-2025-01-07": "simple", "COIN-2025-01-07": "simple", "MSFT-2025-01-07": "all_signals", "META-2025-01-07": "all_signals", "AMZN-2025-01-07": "all_signals", "AMD-2025-01-07": "simple", "INTC-2025-01-07": "all_signals", "LCID-2025-01-07": "all_signals", "QUBT-2025-01-07": "all_signals", "BTCUSD-2025-01-07": "simple", "ETHUSD-2025-01-07": "all_signals", "UNIUSD-2025-01-07": "highlow", "COUR-2025-01-08": "all_signals", "GOOG-2025-01-08": "simple", "TSLA-2025-01-08": "all_signals", "NVDA-2025-01-08": "all_signals", "AAPL-2025-01-08": "all_signals", "U-2025-01-08": "all_signals", "ADSK-2025-01-08": "simple", "CRWD-2025-01-08": "simple", "ADBE-2025-01-08": "all_signals", "NET-2025-01-08": "simple", "COIN-2025-01-08": "simple", "MSFT-2025-01-08": "all_signals", "META-2025-01-08": "all_signals", "AMZN-2025-01-08": "all_signals", "AMD-2025-01-08": "simple", "INTC-2025-01-08": "all_signals", "LCID-2025-01-08": "simple", "QUBT-2025-01-08": "all_signals", "BTCUSD-2025-01-08": "simple", "ETHUSD-2025-01-08": "all_signals", "UNIUSD-2025-01-08": "highlow", "COUR-2025-01-09": "all_signals", "GOOG-2025-01-09": "simple", "TSLA-2025-01-09": "all_signals", "NVDA-2025-01-09": "simple", "AAPL-2025-01-09": "all_signals", "U-2025-01-09": "all_signals", "ADSK-2025-01-09": "simple", "CRWD-2025-01-09": "simple", "ADBE-2025-01-09": "all_signals", "NET-2025-01-09": "simple", "COIN-2025-01-09": "simple", "MSFT-2025-01-09": "all_signals", "META-2025-01-09": "all_signals", "AMZN-2025-01-09": "all_signals", "AMD-2025-01-09": "simple", "INTC-2025-01-09": "simple", "LCID-2025-01-09": "all_signals", "QUBT-2025-01-09": "all_signals", "BTCUSD-2025-01-09": "simple", "ETHUSD-2025-01-09": "all_signals", "UNIUSD-2025-01-09": "highlow", "BTCUSD-2025-01-10": "simple", "ETHUSD-2025-01-10": "simple", "UNIUSD-2025-01-10": "simple", "COUR-2025-01-11": "simple", "GOOG-2025-01-11": "simple", "TSLA-2025-01-11": "all_signals", "NVDA-2025-01-11": "simple", "AAPL-2025-01-11": "all_signals", "U-2025-01-11": "all_signals", "ADSK-2025-01-11": "all_signals", "CRWD-2025-01-11": "simple", "ADBE-2025-01-11": "simple", "NET-2025-01-11": "all_signals", "COIN-2025-01-11": "all_signals", "MSFT-2025-01-11": "simple", "META-2025-01-11": "simple", "AMZN-2025-01-11": "all_signals", "AMD-2025-01-11": "simple", "INTC-2025-01-11": "all_signals", "LCID-2025-01-11": "simple", "QUBT-2025-01-11": "all_signals", "BTCUSD-2025-01-11": "simple", "ETHUSD-2025-01-11": "simple", "UNIUSD-2025-01-11": "all_signals", "BTCUSD-2025-01-12": "simple", "ETHUSD-2025-01-12": "all_signals", "UNIUSD-2025-01-12": "all_signals", "BTCUSD-2025-01-13": "simple", "ETHUSD-2025-01-13": "simple", "UNIUSD-2025-01-13": "all_signals", "COUR-2025-01-14": "simple", "GOOG-2025-01-14": "simple", "TSLA-2025-01-14": "all_signals", "NVDA-2025-01-14": "simple", "AAPL-2025-01-14": "all_signals", "U-2025-01-14": "all_signals", "ADSK-2025-01-14": "all_signals", "CRWD-2025-01-14": "simple", "ADBE-2025-01-14": "simple", "NET-2025-01-14": "all_signals", "COIN-2025-01-14": "all_signals", "MSFT-2025-01-14": "simple", "META-2025-01-14": "simple", "AMZN-2025-01-14": "all_signals", "AMD-2025-01-14": "simple", "INTC-2025-01-14": "all_signals", "LCID-2025-01-14": "all_signals", "QUBT-2025-01-14": "all_signals", "BTCUSD-2025-01-14": "simple", "ETHUSD-2025-01-14": "all_signals", "UNIUSD-2025-01-14": "all_signals", "COUR-2025-01-15": "simple", "GOOG-2025-01-15": "simple", "TSLA-2025-01-15": "all_signals", "NVDA-2025-01-15": "simple", "AAPL-2025-01-15": "all_signals", "U-2025-01-15": "all_signals", "ADSK-2025-01-15": "all_signals", "CRWD-2025-01-15": "simple", "ADBE-2025-01-15": "simple", "NET-2025-01-15": "all_signals", "COIN-2025-01-15": "simple", "MSFT-2025-01-15": "simple", "META-2025-01-15": "simple", "AMZN-2025-01-15": "all_signals", "AMD-2025-01-15": "simple", "INTC-2025-01-15": "all_signals", "LCID-2025-01-15": "all_signals", "QUBT-2025-01-15": "all_signals", "BTCUSD-2025-01-15": "simple", "ETHUSD-2025-01-15": "simple", "UNIUSD-2025-01-15": "all_signals", "COUR-2025-01-16": "simple", "GOOG-2025-01-16": "simple", "TSLA-2025-01-16": "all_signals", "NVDA-2025-01-16": "simple", "AAPL-2025-01-16": "all_signals", "U-2025-01-16": "all_signals", "ADSK-2025-01-16": "all_signals", "CRWD-2025-01-16": "simple", "ADBE-2025-01-16": "simple", "NET-2025-01-16": "all_signals", "COIN-2025-01-16": "all_signals", "MSFT-2025-01-16": "simple", "META-2025-01-16": "simple", "AMZN-2025-01-16": "all_signals", "AMD-2025-01-16": "simple", "INTC-2025-01-16": "all_signals", "LCID-2025-01-16": "all_signals", "QUBT-2025-01-16": "all_signals", "BTCUSD-2025-01-16": "simple", "ETHUSD-2025-01-16": "simple", "UNIUSD-2025-01-16": "simple", "COUR-2025-01-17": "simple", "GOOG-2025-01-17": "simple", "TSLA-2025-01-17": "all_signals", "NVDA-2025-01-17": "simple", "AAPL-2025-01-17": "all_signals", "U-2025-01-17": "all_signals", "ADSK-2025-01-17": "all_signals", "CRWD-2025-01-17": "simple", "ADBE-2025-01-17": "simple", "NET-2025-01-17": "all_signals", "COIN-2025-01-17": "all_signals", "MSFT-2025-01-17": "simple", "META-2025-01-17": "simple", "AMZN-2025-01-17": "all_signals", "AMD-2025-01-17": "simple", "INTC-2025-01-17": "all_signals", "LCID-2025-01-17": "all_signals", "QUBT-2025-01-17": "simple", "BTCUSD-2025-01-17": "simple", "ETHUSD-2025-01-17": "simple", "UNIUSD-2025-01-17": "all_signals", "COUR-2025-01-18": "simple", "GOOG-2025-01-18": "simple", "TSLA-2025-01-18": "all_signals", "NVDA-2025-01-18": "simple", "AAPL-2025-01-18": "all_signals", "U-2025-01-18": "all_signals", "ADSK-2025-01-18": "all_signals", "CRWD-2025-01-18": "simple", "ADBE-2025-01-18": "simple", "NET-2025-01-18": "all_signals", "COIN-2025-01-18": "all_signals", "MSFT-2025-01-18": "simple", "META-2025-01-18": "all_signals", "AMZN-2025-01-18": "all_signals", "AMD-2025-01-18": "simple", "INTC-2025-01-18": "all_signals", "LCID-2025-01-18": "all_signals", "QUBT-2025-01-18": "simple", "BTCUSD-2025-01-18": "simple", "ETHUSD-2025-01-18": "simple", "UNIUSD-2025-01-18": "all_signals", "BTCUSD-2025-01-19": "simple", "ETHUSD-2025-01-19": "all_signals", "UNIUSD-2025-01-19": "all_signals", "BTCUSD-2025-01-20": "simple", "ETHUSD-2025-01-20": "simple", "UNIUSD-2025-01-20": "all_signals", "BTCUSD-2025-01-21": "simple", "ETHUSD-2025-01-21": "simple", "UNIUSD-2025-01-21": "all_signals", "COUR-2025-01-22": "simple", "GOOG-2025-01-22": "simple", "TSLA-2025-01-22": "all_signals", "NVDA-2025-01-22": "all_signals", "AAPL-2025-01-22": "all_signals", "U-2025-01-22": "all_signals", "ADSK-2025-01-22": "all_signals", "CRWD-2025-01-22": "simple", "ADBE-2025-01-22": "simple", "NET-2025-01-22": "all_signals", "COIN-2025-01-22": "all_signals", "MSFT-2025-01-22": "simple", "META-2025-01-22": "all_signals", "AMZN-2025-01-22": "all_signals", "AMD-2025-01-22": "simple", "INTC-2025-01-22": "all_signals", "LCID-2025-01-22": "all_signals", "QUBT-2025-01-22": "all_signals", "BTCUSD-2025-01-22": "simple", "ETHUSD-2025-01-22": "simple", "UNIUSD-2025-01-22": "all_signals", "COUR-2025-01-23": "simple", "GOOG-2025-01-23": "simple", "TSLA-2025-01-23": "all_signals", "NVDA-2025-01-23": "simple", "AAPL-2025-01-23": "all_signals", "U-2025-01-23": "all_signals", "ADSK-2025-01-23": "all_signals", "CRWD-2025-01-23": "simple", "ADBE-2025-01-23": "simple", "NET-2025-01-23": "all_signals", "COIN-2025-01-23": "all_signals", "MSFT-2025-01-23": "simple", "META-2025-01-23": "simple", "AMZN-2025-01-23": "all_signals", "AMD-2025-01-23": "simple", "INTC-2025-01-23": "all_signals", "LCID-2025-01-23": "all_signals", "QUBT-2025-01-23": "simple", "BTCUSD-2025-01-23": "simple", "ETHUSD-2025-01-23": "simple", "UNIUSD-2025-01-23": "all_signals", "COUR-2025-01-24": "simple", "GOOG-2025-01-24": "simple", "TSLA-2025-01-24": "all_signals", "NVDA-2025-01-24": "simple", "AAPL-2025-01-24": "all_signals", "U-2025-01-24": "all_signals", "ADSK-2025-01-24": "all_signals", "CRWD-2025-01-24": "simple", "ADBE-2025-01-24": "simple", "NET-2025-01-24": "all_signals", "COIN-2025-01-24": "all_signals", "MSFT-2025-01-24": "simple", "META-2025-01-24": "simple", "AMZN-2025-01-24": "all_signals", "AMD-2025-01-24": "simple", "INTC-2025-01-24": "all_signals", "LCID-2025-01-24": "all_signals", "QUBT-2025-01-24": "simple", "BTCUSD-2025-01-24": "simple", "ETHUSD-2025-01-24": "simple", "UNIUSD-2025-01-24": "all_signals", "COUR-2025-01-25": "simple", "GOOG-2025-01-25": "simple", "TSLA-2025-01-25": "all_signals", "NVDA-2025-01-25": "simple", "AAPL-2025-01-25": "all_signals", "U-2025-01-25": "all_signals", "ADSK-2025-01-25": "simple", "CRWD-2025-01-25": "simple", "ADBE-2025-01-25": "simple", "NET-2025-01-25": "all_signals", "COIN-2025-01-25": "all_signals", "MSFT-2025-01-25": "simple", "META-2025-01-25": "all_signals", "AMZN-2025-01-25": "all_signals", "AMD-2025-01-25": "all_signals", "INTC-2025-01-25": "all_signals", "LCID-2025-01-25": "all_signals", "QUBT-2025-01-25": "simple", "BTCUSD-2025-01-25": "simple", "ETHUSD-2025-01-25": "simple", "UNIUSD-2025-01-25": "all_signals"}