{
  "symbol": "LINKUSD",
  "model": "chronos2",
  "config": {
    "name": "chronos2_ctx1024_bs2048_val20_test20",
    "model_id": "chronos2",
    "device_map": "cuda",
    "context_length": 1024,
    "prediction_length": 1,
    "quantile_levels": [
      0.1,
      0.5,
      0.9
    ],
    "batch_size": 2048
  },
  "validation": {
    "price_mae": 0.6864423751831055,
    "pct_return_mae": 0.028674484954671044,
    "latency_s": 0.20446360705100233
  },
  "test": {
    "price_mae": 0.5699775695800782,
    "pct_return_mae": 0.025124477188226097,
    "latency_s": 0.20671372984725167
  },
  "windows": {
    "val_window": 20,
    "test_window": 20,
    "forecast_horizon": 1
  },
  "metadata": {
    "source": "chronos2_hyperparam_eval",
    "generated_at": "2025-11-13T00:53:32.237956+00:00",
    "evaluated_windows": 40,
    "repeats": 1,
    "context_length": 1024,
    "batch_size": 2048
  }
}