{
  "epochs": 20,
  "hidden_dim": 256,
  "n_layers": 4,
  "run_name": "bitbank_20ep",
  "result": {
    "total_return": 0.15521879332151323,
    "sortino": 128.85051320965138,
    "final_equity": 11552.395453671379
  },
  "history": [
    {
      "epoch": 1,
      "val_sortino": 181.25693003336588,
      "val_return": 3.9238929748535156
    },
    {
      "epoch": 2,
      "val_sortino": 319.45008850097656,
      "val_return": 3.5224337577819824
    },
    {
      "epoch": 3,
      "val_sortino": 376.6573181152344,
      "val_return": 4.343478838602702
    },
    {
      "epoch": 4,
      "val_sortino": 369.2813186645508,
      "val_return": 4.625233014424642
    },
    {
      "epoch": 5,
      "val_sortino": 515.4545186360677,
      "val_return": 7.182108561197917
    },
    {
      "epoch": 6,
      "val_sortino": 415.4753697713216,
      "val_return": 6.621610005696614
    },
    {
      "epoch": 7,
      "val_sortino": 367.44884236653644,
      "val_return": 6.436126629511516
    },
    {
      "epoch": 8,
      "val_sortino": 307.63390096028644,
      "val_return": 6.427992820739746
    },
    {
      "epoch": 9,
      "val_sortino": 305.94196065266925,
      "val_return": 6.088590780893962
    },
    {
      "epoch": 10,
      "val_sortino": 352.0755157470703,
      "val_return": 9.479164441426596
    },
    {
      "epoch": 11,
      "val_sortino": 282.11619059244794,
      "val_return": 8.29260810216268
    },
    {
      "epoch": 12,
      "val_sortino": 292.0999018351237,
      "val_return": 9.487194697062174
    },
    {
      "epoch": 13,
      "val_sortino": 298.3946889241536,
      "val_return": 7.46178921063741
    },
    {
      "epoch": 14,
      "val_sortino": 314.9645233154297,
      "val_return": 8.52072842915853
    },
    {
      "epoch": 15,
      "val_sortino": 291.1571451822917,
      "val_return": 9.712658246358236
    },
    {
      "epoch": 16,
      "val_sortino": 328.3750508626302,
      "val_return": 8.154762585957846
    },
    {
      "epoch": 17,
      "val_sortino": 253.39089965820312,
      "val_return": 11.764864603678385
    },
    {
      "epoch": 18,
      "val_sortino": 347.24294026692706,
      "val_return": 8.90341583887736
    },
    {
      "epoch": 19,
      "val_sortino": 398.57042439778644,
      "val_return": 10.82129430770874
    },
    {
      "epoch": 20,
      "val_sortino": 481.0977783203125,
      "val_return": 9.409079869588217
    }
  ]
}